pylxpweb/__init__.py
pylxpweb/api_namespace.py
pylxpweb/cli/README.md
pylxpweb/cli/__init__.py
pylxpweb/cli/collect_device_data.py
pylxpweb/cli/collectors/__init__.py
pylxpweb/cli/collectors/base.py
pylxpweb/cli/collectors/cloud.py
pylxpweb/cli/collectors/dongle.py
pylxpweb/cli/collectors/modbus.py
pylxpweb/cli/formatters/__init__.py
pylxpweb/cli/formatters/archive.py
pylxpweb/cli/formatters/base.py
pylxpweb/cli/formatters/binary.py
pylxpweb/cli/formatters/csv_fmt.py
pylxpweb/cli/formatters/json_fmt.py
pylxpweb/cli/formatters/markdown.py
pylxpweb/cli/modbus_diag.py
pylxpweb/cli/utils/__init__.py
pylxpweb/cli/utils/github.py
pylxpweb/cli/utils/prompts.py
pylxpweb/cli/utils/sanitize.py
pylxpweb/cli/utils/serial_detect.py
pylxpweb/client.py
pylxpweb/constants/__init__.py
pylxpweb/constants/api.py
pylxpweb/constants/devices.py
pylxpweb/constants/locations.py
pylxpweb/constants/registers.py
pylxpweb/constants/scaling.py
pylxpweb/devices/__init__.py
pylxpweb/devices/_firmware_update_mixin.py
pylxpweb/devices/_mid_runtime_properties.py
pylxpweb/devices/base.py
pylxpweb/devices/battery.py
pylxpweb/devices/battery_bank.py
pylxpweb/devices/discovery.py
pylxpweb/devices/inverters/__init__.py
pylxpweb/devices/inverters/_features.py
pylxpweb/devices/inverters/_runtime_properties.py
pylxpweb/devices/inverters/base.py
pylxpweb/devices/inverters/generic.py
pylxpweb/devices/inverters/hybrid.py
pylxpweb/devices/mid_device.py
pylxpweb/devices/models.py
pylxpweb/devices/parallel_group.py
pylxpweb/devices/station.py
pylxpweb/endpoints/__init__.py
pylxpweb/endpoints/analytics.py
pylxpweb/endpoints/base.py
pylxpweb/endpoints/control.py
pylxpweb/endpoints/devices.py
pylxpweb/endpoints/export.py
pylxpweb/endpoints/firmware.py
pylxpweb/endpoints/forecasting.py
pylxpweb/endpoints/plants.py
pylxpweb/exceptions.py
pylxpweb/models.py
pylxpweb/py.typed
pylxpweb/registers.py
pylxpweb/scanner/__init__.py
pylxpweb/scanner/mac_lookup.py
pylxpweb/scanner/scanner.py
pylxpweb/scanner/types.py
pylxpweb-0.6.9.dist-info/WHEEL
pylxpweb-0.6.9.dist-info/entry_points.txt
pylxpweb-0.6.9.dist-info/METADATA
pylxpweb-0.6.9.dist-info/RECORD
