Metadata-Version: 2.3
Name: pylxpweb
Version: 0.6.9
Summary: Python client library for Luxpower/EG4 inverter web monitoring API
Keywords: luxpower,eg4,inverter,solar,api,client
Author: Bryan Li
Author-email: Bryan Li <bryan.li@gmail.com>
License: MIT
Classifier: Development Status :: 3 - Alpha
Classifier: Intended Audience :: Developers
Classifier: License :: OSI Approved :: MIT License
Classifier: Programming Language :: Python :: 3
Classifier: Programming Language :: Python :: 3.12
Classifier: Programming Language :: Python :: 3.13
Classifier: Topic :: Home Automation
Classifier: Topic :: Software Development :: Libraries :: Python Modules
Requires-Dist: aiohttp>=3.13.2
Requires-Dist: pydantic>=2.12.0
Requires-Dist: pymodbus>=3.6.0
Requires-Dist: pytest>=9.0.1 ; extra == 'dev'
Requires-Dist: pytest-asyncio>=1.3.0 ; extra == 'dev'
Requires-Dist: pytest-cov>=7.0.0 ; extra == 'dev'
Requires-Dist: aioresponses>=0.7.8 ; extra == 'dev'
Requires-Dist: mypy>=1.18.2 ; extra == 'dev'
Requires-Dist: ruff>=0.14.5 ; extra == 'dev'
Requires-Python: >=3.12
Provides-Extra: dev
